gitlab_arc_fs/__init__.py
gitlab_arc_fs/arc_fs.py
gitlab_arc_fs/gitlab_filestream.py
gitlab_arc_fs/lfs_file.py
gitlab_arc_fs/opener.py
gitlab_arc_fs/utils.py
gitlab_arc_fs-0.0.21.dev1.dist-info/licenses/LICENSE
gitlab_arc_fs-0.0.21.dev1.dist-info/METADATA
gitlab_arc_fs-0.0.21.dev1.dist-info/WHEEL
gitlab_arc_fs-0.0.21.dev1.dist-info/entry_points.txt
gitlab_arc_fs-0.0.21.dev1.dist-info/top_level.txt
gitlab_arc_fs-0.0.21.dev1.dist-info/RECORD
