Metadata-Version: 2.4
Name: gitlab_arc_fs
Version: 0.0.21.dev1
Summary: An experimental and GitLab filesystem extension for PyFilesystem2.!
Home-page: https://github.com/nfdi4plants/ARCfs
Author: Julian Weidhase
Author-email: julian.weidhase@rz.uni-freiburg.de
License: GPLv3
Requires-Python: >=3.8
License-File: LICENSE
Requires-Dist: fs>=2.4.16
Requires-Dist: urllib3>=1.26.13
Requires-Dist: requests>=2.28.1
Requires-Dist: aiohttp>=3.8.3
Dynamic: author
Dynamic: author-email
Dynamic: home-page
Dynamic: license
Dynamic: license-file
Dynamic: requires-dist
Dynamic: requires-python
Dynamic: summary
